tgedr/__init__.py
tgedr/pythonlib/example.py
tgedr_pythonlib-0.0.1.dist-info/METADATA
tgedr_pythonlib-0.0.1.dist-info/WHEEL
tgedr_pythonlib-0.0.1.dist-info/top_level.txt
tgedr_pythonlib-0.0.1.dist-info/RECORD
