Metadata-Version: 2.4
Name: tgedr-pythonlib
Version: 0.0.1
Summary: this is a template for a python package
Author-email: developer <developer@email.com>
Requires-Python: >=3.11
Requires-Dist: pandas>=2.3.0
